{
  "name": "@filed/tax-engine",
  "version": "0.0.1",
  "exports": "./mod.ts",
  "imports": {
    "zod": "npm:zod@^3.24",
    "@std/assert": "jsr:@std/assert",
    "@std/fs": "jsr:@std/fs",
    "@std/cli": "jsr:@std/cli",
    "@std/path": "jsr:@std/path"
  },
  "tasks": {
    "tax": "deno run --allow-read --allow-write --allow-run=xsltproc cli/main.ts",
    "test": "deno test --allow-read --allow-write",
    "test:engine": "deno test engine/",
    "test:cli": "deno test --allow-read --allow-write engine/cli/"
  }
}
